eventsourcing_umadb/__init__.py
eventsourcing_umadb/factory.py
eventsourcing_umadb/py.typed
eventsourcing_umadb/recorders.py
eventsourcing_umadb-0.3.2.dist-info/METADATA
eventsourcing_umadb-0.3.2.dist-info/WHEEL
eventsourcing_umadb-0.3.2.dist-info/licenses/LICENSE
eventsourcing_umadb-0.3.2.dist-info/RECORD
