Metadata-Version: 2.4
Name: eventsourcing-umadb
Version: 0.3.2
Summary: Python package for eventsourcing with UmaDB
License: BSD 3-Clause
License-File: LICENSE
Author: John Bywater
Author-email: john.bywater@appropriatesoftware.net
Requires-Python: >=3.10
Classifier: Development Status :: 3 - Alpha
Classifier: License :: OSI Approved :: BSD License
Classifier: Programming Language :: Python :: 3
Classifier: Programming Language :: Python :: 3.10
Classifier: Programming Language :: Python :: 3.11
Classifier: Programming Language :: Python :: 3.12
Classifier: Programming Language :: Python :: 3.13
Classifier: Programming Language :: Python :: 3.14
Classifier: Programming Language :: Python
Requires-Dist: eventsourcing (>=9.5.0)
Requires-Dist: umadb (>=0.2.0)
